remotivelabs/cli/__init__.py
remotivelabs/cli/api/cloud/tokens.py
remotivelabs/cli/broker/__init__.py
remotivelabs/cli/broker/discovery.py
remotivelabs/cli/broker/export.py
remotivelabs/cli/broker/files.py
remotivelabs/cli/broker/lib/__about__.py
remotivelabs/cli/broker/lib/broker.py
remotivelabs/cli/broker/lib/client.py
remotivelabs/cli/broker/lib/helper.py
remotivelabs/cli/broker/lib/signalcreator.py
remotivelabs/cli/broker/license_flows.py
remotivelabs/cli/broker/licenses.py
remotivelabs/cli/broker/playback.py
remotivelabs/cli/broker/record.py
remotivelabs/cli/broker/recording_session/__init__.py
remotivelabs/cli/broker/recording_session/client.py
remotivelabs/cli/broker/recording_session/cmd.py
remotivelabs/cli/broker/recording_session/time.py
remotivelabs/cli/broker/scripting.py
remotivelabs/cli/broker/signals.py
remotivelabs/cli/broker/typer.py
remotivelabs/cli/broker/version.py
remotivelabs/cli/cloud/__init__.py
remotivelabs/cli/cloud/auth/__init__.py
remotivelabs/cli/cloud/auth/cmd.py
remotivelabs/cli/cloud/auth/login.py
remotivelabs/cli/cloud/auth_tokens.py
remotivelabs/cli/cloud/brokers.py
remotivelabs/cli/cloud/configs.py
remotivelabs/cli/cloud/licenses/__init__.py
remotivelabs/cli/cloud/licenses/cmd.py
remotivelabs/cli/cloud/organisations.py
remotivelabs/cli/cloud/projects.py
remotivelabs/cli/cloud/recordings.py
remotivelabs/cli/cloud/recordings_playback.py
remotivelabs/cli/cloud/resumable_upload.py
remotivelabs/cli/cloud/sample_recordings.py
remotivelabs/cli/cloud/service_account_tokens.py
remotivelabs/cli/cloud/service_accounts.py
remotivelabs/cli/cloud/storage/__init__.py
remotivelabs/cli/cloud/storage/cmd.py
remotivelabs/cli/cloud/storage/copy.py
remotivelabs/cli/cloud/storage/uri_or_path.py
remotivelabs/cli/cloud/uri.py
remotivelabs/cli/connect/__init__.py
remotivelabs/cli/connect/connect.py
remotivelabs/cli/connect/protopie/protopie.py
remotivelabs/cli/py.typed
remotivelabs/cli/remotive.py
remotivelabs/cli/settings/__init__.py
remotivelabs_cli-0.5.0.dist-info/licenses/LICENSE
remotivelabs_cli-0.5.0.dist-info/WHEEL
remotivelabs_cli-0.5.0.dist-info/entry_points.txt
remotivelabs_cli-0.5.0.dist-info/METADATA
remotivelabs_cli-0.5.0.dist-info/RECORD
